scopectx/__init__.py
scopectx-0.2.1.dist-info/DESCRIPTION.rst
scopectx-0.2.1.dist-info/METADATA
scopectx-0.2.1.dist-info/RECORD
scopectx-0.2.1.dist-info/WHEEL
scopectx-0.2.1.dist-info/metadata.json
scopectx-0.2.1.dist-info/top_level.txt
